falocalrepo/__init__.py
falocalrepo/__main__.py
falocalrepo/__version__.py
falocalrepo/console/__init__.py
falocalrepo/console/app.py
falocalrepo/console/colors.py
falocalrepo/console/config.py
falocalrepo/console/database.py
falocalrepo/console/download.py
falocalrepo/console/util.py
falocalrepo/downloader.py
falocalrepo-4.5.2.dist-info/LICENSE
falocalrepo-4.5.2.dist-info/METADATA
falocalrepo-4.5.2.dist-info/WHEEL
falocalrepo-4.5.2.dist-info/entry_points.txt
falocalrepo-4.5.2.dist-info/RECORD
