Metadata-Version: 2.1
Name: falocalrepo
Version: 4.5.2
Summary: Pure Python program to download any user's gallery, scraps, favorites, and journals from FurAffinity in an easily handled database.
Home-page: https://github.com/FurryCoders/FALocalRepo
License: EUPL-1.2
Author: Matteo Campinoti
Author-email: matteo.campinoti94@gmail.com
Requires-Python: >=3.10,<4.0
Classifier: Development Status :: 5 - Production/Stable
Classifier: Intended Audience :: End Users/Desktop
Classifier: License :: OSI Approved :: European Union Public Licence 1.2 (EUPL 1.2)
Classifier: Operating System :: OS Independent
Classifier: Programming Language :: Python :: 3
Classifier: Programming Language :: Python :: 3.10
Classifier: Programming Language :: Python :: 3.11
Classifier: Programming Language :: Python :: 3.12
Classifier: Topic :: Internet :: WWW/HTTP :: Indexing/Search
Classifier: Topic :: Utilities
Requires-Dist: browser-cookie3 (>=0.20.1,<0.21.0)
Requires-Dist: click (>=8.1.7,<9.0.0)
Requires-Dist: click-help-colors (>=0.9.4,<0.10.0)
Requires-Dist: faapi (>=3.11.11,<3.12.0)
Requires-Dist: falocalrepo-database (>=5.4.6,<5.5.0)
Requires-Dist: falocalrepo-server (>=3.4.3,<3.5.0)
Requires-Dist: pretty-errors (>=1.2.25,<2.0.0)
Requires-Dist: wcwidth (>=0.2.13,<0.3.0)
Project-URL: Bug Reports, https://github.com/FurryCoders/FALocalRepo/issues
Project-URL: Changelog, https://github.com/FurryCoders/FALocalRepo/blob/main/CHANGELOG.md
Project-URL: Documentation, https://github.com/FurryCoders/FALocalRepo/wiki
Project-URL: Download, https://pypi.org/project/falocalrepo/#files
Project-URL: Repository, https://github.com/FurryCoders/FALocalRepo
Project-URL: Source, https://github.com/FurryCoders/FALocalRepo
